pyscreener/__init__.py
pyscreener/_version.py
pyscreener/args.py
pyscreener/base.py
pyscreener/exceptions.py
pyscreener/main.py
pyscreener/supply.py
pyscreener/warnings.py
pyscreener/dft/__init__.py
pyscreener/dft/dft.py
pyscreener/dft/preparation.py
pyscreener/docking/__init__.py
pyscreener/docking/calculation.py
pyscreener/docking/metadata.py
pyscreener/docking/result.py
pyscreener/docking/runner.py
pyscreener/docking/screen.py
pyscreener/docking/sim.py
pyscreener/docking/utils.py
pyscreener/docking/dock/__init__.py
pyscreener/docking/dock/exceptions.py
pyscreener/docking/dock/metadata.py
pyscreener/docking/dock/runner.py
pyscreener/docking/dock/utils.py
pyscreener/docking/dock/scripts/__init__.py
pyscreener/docking/dock/scripts/prep_rec.py2
pyscreener/docking/dock/scripts/write_dms.py2
pyscreener/docking/vina/__init__.py
pyscreener/docking/vina/metadata.py
pyscreener/docking/vina/runner.py
pyscreener/docking/vina/utils.py
pyscreener/md/__init__.py
pyscreener/md/md.py
pyscreener/md/preparation.py
pyscreener/postprocessing/__init__.py
pyscreener/postprocessing/cluster.py
pyscreener/postprocessing/fingerprints.py
pyscreener/postprocessing/hist.py
pyscreener/preprocessing/filter.py
pyscreener/utils/__init__.py
pyscreener/utils/autobox.py
pyscreener/utils/pdbfix.py
pyscreener/utils/utils.py
pyscreener-1.2.3.dist-info/LICENSE
pyscreener-1.2.3.dist-info/METADATA
pyscreener-1.2.3.dist-info/WHEEL
pyscreener-1.2.3.dist-info/entry_points.txt
pyscreener-1.2.3.dist-info/top_level.txt
pyscreener-1.2.3.dist-info/RECORD
