Metadata-Version: 2.1
Name: pyscreener
Version: 1.2.3
Summary: pythonic interface to virtual screening software
Home-page: https://github.com/coleygroup/pyscreener
Author: david graff
Author-email: deg711@g.harvard.edu
License: MIT
Platform: Linux
Platform: Mac OS-X
Platform: Unix
Classifier: Framework :: Pytest
Classifier: Intended Audience :: Science/Research
Classifier: License :: OSI Approved :: MIT License
Classifier: Programming Language :: Python :: 3
Classifier: Programming Language :: Python :: 3.8
Classifier: Topic :: Scientific/Engineering :: Bio-Informatics
Classifier: Topic :: Scientific/Engineering :: Chemistry
Requires-Python: >=3.8
License-File: LICENSE
Requires-Dist: colorama
Requires-Dist: configargparse
Requires-Dist: h5py
Requires-Dist: numpy
Requires-Dist: pandas
Requires-Dist: pdbfixer
Requires-Dist: ray[default] (>=2.0)
Requires-Dist: scipy
Requires-Dist: tqdm
Provides-Extra: dev
Requires-Dist: black ; extra == 'dev'
Requires-Dist: bumpversion ; extra == 'dev'
Requires-Dist: flake8 ; extra == 'dev'
Requires-Dist: pre-commit ; extra == 'dev'
Requires-Dist: pytest ; extra == 'dev'
Provides-Extra: test
Requires-Dist: pytest ; extra == 'test'
Provides-Extra: viz
Requires-Dist: matplotlib ; extra == 'viz'
Requires-Dist: seaborn ; extra == 'viz'
